glean/__init__.py
glean/cli.py
glean/constants.py
glean/credentials.py
glean/filesystem.py
glean/api/__init__.py
glean/api/access_keys/__init__.py
glean/api/access_keys/browser_auth.py
glean/api/access_keys/existing_user.py
glean/api/access_keys/new_user.py
glean/api/access_keys/utils.py
glean/api/analytics/__init__.py
glean/api/analytics/cli_with_tracking.py
glean/api/analytics/events.py
glean/utils/__init__.py
glean/utils/cli.py
glean/utils/grn.py
glean/utils/input_validation.py
glean/utils/resource.py
glean/utils/validate_config.py
glean_cli-0.9.2.dist-info/LICENSE
glean_cli-0.9.2.dist-info/METADATA
glean_cli-0.9.2.dist-info/WHEEL
glean_cli-0.9.2.dist-info/entry_points.txt
glean_cli-0.9.2.dist-info/top_level.txt
glean_cli-0.9.2.dist-info/RECORD
