Metadata-Version: 2.1
Name: glean-cli
Version: 0.9.2
Summary: Command-line tools for interacting with Glean
Home-page: https://glean.io/
Author: Dan Eisenberg
Author-email: dse@glean.io
Classifier: Programming Language :: Python :: 3
Classifier: License :: OSI Approved :: Apache Software License
Classifier: Operating System :: OS Independent
Requires-Python: >=3.7
License-File: LICENSE
Requires-Dist: Click >=8.0
Requires-Dist: pyyaml >=6.0
Requires-Dist: requests >=2.0
Requires-Dist: ruamel.yaml >=0.17
Requires-Dist: yaspin >=2.1.0
Requires-Dist: semver >=3.0.1
Provides-Extra: test
Requires-Dist: pytest ; extra == 'test'
Requires-Dist: cram ; extra == 'test'
